wheeel/__about__.py
wheeel/__init__.py
wheeel-0.0.1.dist-info/METADATA
wheeel-0.0.1.dist-info/WHEEL
wheeel-0.0.1.dist-info/entry_points.txt
wheeel-0.0.1.dist-info/licenses/LICENSE.txt
wheeel-0.0.1.dist-info/RECORD
